{
  "stock_list_VN": {
    "updated": "2026-06-01T22:44:38.115360",
    "count": 4218
  },
  "price_VCB_VN": {
    "updated": "2026-06-01T21:16:36.353663",
    "rows": 862,
    "start": "2022-12-22 00:00:00",
    "end": "2026-05-29 00:00:00"
  },
  "price_HPG_VN": {
    "updated": "2026-06-01T21:24:17.095596",
    "rows": 853,
    "start": "2022-12-22 00:00:00",
    "end": "2026-06-01 00:00:00"
  },
  "price_HAG_VN": {
    "updated": "2026-06-01T21:21:09.952734",
    "rows": 885,
    "start": "2022-11-08 00:00:00",
    "end": "2026-06-01 00:00:00"
  },
  "price_PNJ_VN": {
    "updated": "2026-06-01T21:28:30.656835",
    "rows": 21,
    "start": "2026-05-04 00:00:00",
    "end": "2026-06-01 00:00:00"
  },
  "price_BSR_VN": {
    "updated": "2026-06-01T21:24:47.699506",
    "rows": 429,
    "start": "2024-08-26 00:00:00",
    "end": "2026-06-01 00:00:00"
  },
  "price_PVS_VN": {
    "updated": "2026-06-01T21:23:36.432137",
    "rows": 429,
    "start": "2024-09-09 00:00:00",
    "end": "2026-06-01 00:00:00"
  },
  "price_NT2_VN": {
    "updated": "2026-06-01T21:26:20.785969",
    "rows": 427,
    "start": "2024-09-11 00:00:00",
    "end": "2026-06-01 00:00:00"
  },
  "price_VNINDEX_VN": {
    "updated": "2026-06-01T21:16:37.107009",
    "rows": 853,
    "start": "2022-12-22 00:00:00",
    "end": "2026-06-01 00:00:00"
  },
  "price_ACB_VN": {
    "updated": "2026-06-01T21:17:32.778017",
    "rows": 853,
    "start": "2022-12-22 00:00:00",
    "end": "2026-06-01 00:00:00"
  },
  "price_BID_VN": {
    "updated": "2026-06-01T21:16:49.085668",
    "rows": 853,
    "start": "2022-12-22 00:00:00",
    "end": "2026-06-01 00:00:00"
  },
  "price_CTG_VN": {
    "updated": "2026-06-01T21:16:59.340061",
    "rows": 853,
    "start": "2022-12-22 00:00:00",
    "end": "2026-06-01 00:00:00"
  },
  "price_FPT_VN": {
    "updated": "2026-06-01T21:30:17.125984",
    "rows": 853,
    "start": "2022-12-22 00:00:00",
    "end": "2026-06-01 00:00:00"
  },
  "price_GAS_VN": {
    "updated": "2026-06-01T21:24:04.238846",
    "rows": 853,
    "start": "2022-12-22 00:00:00",
    "end": "2026-06-01 00:00:00"
  },
  "price_GVR_VN": {
    "updated": "2026-06-01T21:24:37.700647",
    "rows": 160,
    "start": "2025-10-07 00:00:00",
    "end": "2026-06-01 00:00:00"
  },
  "price_HDB_VN": {
    "updated": "2026-06-01T21:18:04.284437",
    "rows": 853,
    "start": "2022-12-22 00:00:00",
    "end": "2026-06-01 00:00:00"
  },
  "price_MBB_VN": {
    "updated": "2026-06-01T21:17:22.708393",
    "rows": 853,
    "start": "2022-12-22 00:00:00",
    "end": "2026-06-01 00:00:00"
  },
  "price_MSN_VN": {
    "updated": "2026-06-01T21:27:58.154418",
    "rows": 853,
    "start": "2022-12-22 00:00:00",
    "end": "2026-06-01 00:00:00"
  },
  "price_MWG_VN": {
    "updated": "2026-06-01T21:28:20.710995",
    "rows": 853,
    "start": "2022-12-22 00:00:00",
    "end": "2026-06-01 00:00:00"
  },
  "price_PLX_VN": {
    "updated": "2026-06-01T21:24:27.739109",
    "rows": 853,
    "start": "2022-12-22 00:00:00",
    "end": "2026-06-01 00:00:00"
  },
  "price_POW_VN": {
    "updated": "2026-06-01T21:26:30.958034",
    "rows": 853,
    "start": "2022-12-22 00:00:00",
    "end": "2026-06-01 00:00:00"
  },
  "price_SAB_VN": {
    "updated": "2026-06-01T21:27:48.142321",
    "rows": 853,
    "start": "2022-12-22 00:00:00",
    "end": "2026-06-01 00:00:00"
  },
  "price_SHB_VN": {
    "updated": "2026-06-01T21:19:20.832424",
    "rows": 853,
    "start": "2022-12-22 00:00:00",
    "end": "2026-06-01 00:00:00"
  },
  "price_SSB_VN": {
    "updated": "2026-06-01T21:18:32.778977",
    "rows": 853,
    "start": "2022-12-22 00:00:00",
    "end": "2026-06-01 00:00:00"
  },
  "price_SSI_VN": {
    "updated": "2026-06-01T21:31:11.272491",
    "rows": 853,
    "start": "2022-12-22 00:00:00",
    "end": "2026-06-01 00:00:00"
  },
  "price_STB_VN": {
    "updated": "2026-06-01T21:17:53.035235",
    "rows": 853,
    "start": "2022-12-22 00:00:00",
    "end": "2026-06-01 00:00:00"
  },
  "price_TCB_VN": {
    "updated": "2026-06-01T21:17:10.702377",
    "rows": 853,
    "start": "2022-12-22 00:00:00",
    "end": "2026-06-01 00:00:00"
  },
  "price_TPB_VN": {
    "updated": "2026-06-01T21:19:01.197275",
    "rows": 853,
    "start": "2022-12-22 00:00:00",
    "end": "2026-06-01 00:00:00"
  },
  "price_VHM_VN": {
    "updated": "2026-06-01T21:19:47.544212",
    "rows": 853,
    "start": "2022-12-22 00:00:00",
    "end": "2026-06-01 00:00:00"
  },
  "price_VIB_VN": {
    "updated": "2026-05-26T21:35:08.959467",
    "rows": 848,
    "start": "2022-12-22 00:00:00",
    "end": "2026-05-25 00:00:00"
  },
  "price_VIC_VN": {
    "updated": "2026-06-01T21:19:37.871624",
    "rows": 853,
    "start": "2022-12-22 00:00:00",
    "end": "2026-06-01 00:00:00"
  },
  "price_VJC_VN": {
    "updated": "2026-06-01T21:30:48.994162",
    "rows": 853,
    "start": "2022-12-22 00:00:00",
    "end": "2026-06-01 00:00:00"
  },
  "price_VNM_VN": {
    "updated": "2026-06-01T21:28:08.149107",
    "rows": 853,
    "start": "2022-12-22 00:00:00",
    "end": "2026-06-01 00:00:00"
  },
  "price_VPB_VN": {
    "updated": "2026-06-01T21:17:42.835879",
    "rows": 853,
    "start": "2022-12-22 00:00:00",
    "end": "2026-06-01 00:00:00"
  },
  "price_VRE_VN": {
    "updated": "2026-06-01T21:19:56.784354",
    "rows": 853,
    "start": "2022-12-22 00:00:00",
    "end": "2026-06-01 00:00:00"
  },
  "price_BVH_VN": {
    "updated": "2026-06-01T21:33:46.579869",
    "rows": 853,
    "start": "2022-12-22 00:00:00",
    "end": "2026-06-01 00:00:00"
  },
  "price_BCM_VN": {
    "updated": "2026-06-01T21:33:56.513531",
    "rows": 853,
    "start": "2022-12-22 00:00:00",
    "end": "2026-06-01 00:00:00"
  },
  "price_PVD_VN": {
    "updated": "2026-06-01T21:23:41.760349",
    "rows": 429,
    "start": "2024-09-09 00:00:00",
    "end": "2026-06-01 00:00:00"
  },
  "price_DPM_VN": {
    "updated": "2026-06-01T21:33:02.970136",
    "rows": 423,
    "start": "2024-09-17 00:00:00",
    "end": "2026-06-01 00:00:00"
  },
  "price_PAN_VN": {
    "updated": "2026-06-01T21:29:06.324077",
    "rows": 422,
    "start": "2024-09-18 00:00:00",
    "end": "2026-06-01 00:00:00"
  },
  "price_PVT_VN": {
    "updated": "2026-06-01T21:23:51.746719",
    "rows": 422,
    "start": "2024-09-18 00:00:00",
    "end": "2026-06-01 00:00:00"
  },
  "price_PGC_VN": {
    "updated": "2026-03-02T21:20:11.519935",
    "rows": 360,
    "start": "2024-09-18 00:00:00",
    "end": "2026-03-02 00:00:00"
  },
  "price_PLC_VN": {
    "updated": "2026-03-02T21:27:09.250221",
    "rows": 360,
    "start": "2024-09-18 00:00:00",
    "end": "2026-03-02 00:00:00"
  },
  "stock_list_TW": {
    "updated": "2026-05-24T22:13:22.759376",
    "count": 1979
  },
  "price_BKC_VN": {
    "updated": "2026-05-15T08:14:02.293894",
    "rows": 88,
    "start": "2025-12-30 00:00:00",
    "end": "2026-05-14 00:00:00"
  },
  "price_VNG_VN": {
    "updated": "2026-05-15T08:14:05.059895",
    "rows": 88,
    "start": "2025-12-11 00:00:00",
    "end": "2026-05-14 00:00:00"
  },
  "price_KOS_VN": {
    "updated": "2026-05-15T08:14:07.737413",
    "rows": 88,
    "start": "2025-12-30 00:00:00",
    "end": "2026-05-14 00:00:00"
  },
  "price_THT_VN": {
    "updated": "2026-05-15T08:14:10.616766",
    "rows": 88,
    "start": "2025-12-30 00:00:00",
    "end": "2026-05-14 00:00:00"
  },
  "price_MHC_VN": {
    "updated": "2026-05-15T08:14:13.398512",
    "rows": 88,
    "start": "2025-12-29 00:00:00",
    "end": "2026-05-14 00:00:00"
  },
  "price_PGI_VN": {
    "updated": "2026-05-15T08:14:16.043282",
    "rows": 88,
    "start": "2025-12-03 00:00:00",
    "end": "2026-05-14 00:00:00"
  },
  "price_SBT_VN": {
    "updated": "2026-05-15T08:14:18.989611",
    "rows": 88,
    "start": "2025-12-30 00:00:00",
    "end": "2026-05-14 00:00:00"
  },
  "price_NBW_VN": {
    "updated": "2026-05-15T08:14:21.900935",
    "rows": 88,
    "start": "2025-10-29 00:00:00",
    "end": "2026-05-12 00:00:00"
  },
  "price_CST_VN": {
    "updated": "2026-05-15T08:14:24.538525",
    "rows": 88,
    "start": "2025-12-29 00:00:00",
    "end": "2026-05-14 00:00:00"
  },
  "price_WSS_VN": {
    "updated": "2026-05-15T08:14:33.081405",
    "rows": 88,
    "start": "2025-12-29 00:00:00",
    "end": "2026-05-14 00:00:00"
  },
  "price_TNG_VN": {
    "updated": "2026-05-15T08:14:36.002829",
    "rows": 88,
    "start": "2025-12-30 00:00:00",
    "end": "2026-05-14 00:00:00"
  },
  "price_VNL_VN": {
    "updated": "2026-05-15T08:14:38.674438",
    "rows": 88,
    "start": "2025-12-30 00:00:00",
    "end": "2026-05-14 00:00:00"
  },
  "price_KHP_VN": {
    "updated": "2026-06-01T21:26:59.883826",
    "rows": 21,
    "start": "2026-05-04 00:00:00",
    "end": "2026-06-01 00:00:00"
  },
  "price_HTN_VN": {
    "updated": "2026-05-15T08:14:44.463628",
    "rows": 88,
    "start": "2025-12-30 00:00:00",
    "end": "2026-05-14 00:00:00"
  },
  "price_TCL_VN": {
    "updated": "2026-05-15T08:14:47.125095",
    "rows": 88,
    "start": "2025-12-30 00:00:00",
    "end": "2026-05-14 00:00:00"
  },
  "price_TNT_VN": {
    "updated": "2026-05-15T08:14:52.772041",
    "rows": 88,
    "start": "2025-12-30 00:00:00",
    "end": "2026-05-14 00:00:00"
  },
  "price_KDM_VN": {
    "updated": "2026-05-15T08:16:17.901055",
    "rows": 88,
    "start": "2025-12-30 00:00:00",
    "end": "2026-05-14 00:00:00"
  },
  "price_FDC_VN": {
    "updated": "2026-05-15T08:16:20.056772",
    "rows": 88,
    "start": "2024-12-20 00:00:00",
    "end": "2026-05-14 00:00:00"
  },
  "price_DST_VN": {
    "updated": "2026-05-15T08:16:22.164096",
    "rows": 88,
    "start": "2025-12-30 00:00:00",
    "end": "2026-05-14 00:00:00"
  },
  "price_VCM_VN": {
    "updated": "2026-05-15T08:16:24.169560",
    "rows": 88,
    "start": "2025-10-17 00:00:00",
    "end": "2026-05-14 00:00:00"
  },
  "price_CDC_VN": {
    "updated": "2026-05-24T10:57:53.116882",
    "rows": 248,
    "start": "2025-05-26 00:00:00",
    "end": "2026-05-22 00:00:00"
  },
  "price_TDP_VN": {
    "updated": "2026-05-15T08:16:28.280577",
    "rows": 88,
    "start": "2025-12-30 00:00:00",
    "end": "2026-05-14 00:00:00"
  },
  "price_CTF_VN": {
    "updated": "2026-05-24T10:57:56.869879",
    "rows": 248,
    "start": "2025-05-26 00:00:00",
    "end": "2026-05-22 00:00:00"
  },
  "price_HLC_VN": {
    "updated": "2026-05-15T08:16:34.519430",
    "rows": 88,
    "start": "2025-12-29 00:00:00",
    "end": "2026-05-14 00:00:00"
  },
  "price_PVC_VN": {
    "updated": "2026-05-15T08:16:38.619306",
    "rows": 88,
    "start": "2025-12-30 00:00:00",
    "end": "2026-05-14 00:00:00"
  },
  "price_SAM_VN": {
    "updated": "2026-05-15T08:16:42.807539",
    "rows": 88,
    "start": "2025-12-30 00:00:00",
    "end": "2026-05-14 00:00:00"
  },
  "price_VTH_VN": {
    "updated": "2026-05-15T08:16:44.888351",
    "rows": 88,
    "start": "2025-08-29 00:00:00",
    "end": "2026-05-14 00:00:00"
  },
  "price_DTA_VN": {
    "updated": "2026-05-15T08:16:46.874440",
    "rows": 88,
    "start": "2025-12-30 00:00:00",
    "end": "2026-05-14 00:00:00"
  },
  "price_TSB_VN": {
    "updated": "2026-05-15T08:16:48.950583",
    "rows": 88,
    "start": "2025-12-25 00:00:00",
    "end": "2026-05-14 00:00:00"
  },
  "price_TMT_VN": {
    "updated": "2026-05-15T08:16:51.181203",
    "rows": 88,
    "start": "2025-12-29 00:00:00",
    "end": "2026-05-14 00:00:00"
  },
  "price_SGH_VN": {
    "updated": "2026-05-15T08:16:53.297453",
    "rows": 88,
    "start": "2025-06-03 00:00:00",
    "end": "2026-05-14 00:00:00"
  },
  "price_NET_VN": {
    "updated": "2026-05-15T08:16:55.381152",
    "rows": 88,
    "start": "2025-12-26 00:00:00",
    "end": "2026-05-14 00:00:00"
  },
  "price_DSE_VN": {
    "updated": "2026-05-15T08:16:57.487182",
    "rows": 88,
    "start": "2025-12-30 00:00:00",
    "end": "2026-05-14 00:00:00"
  },
  "price_TOT_VN": {
    "updated": "2026-05-15T08:16:59.616762",
    "rows": 88,
    "start": "2025-12-08 00:00:00",
    "end": "2026-05-13 00:00:00"
  },
  "price_RAL_VN": {
    "updated": "2026-05-15T08:17:01.707821",
    "rows": 88,
    "start": "2025-12-30 00:00:00",
    "end": "2026-05-14 00:00:00"
  },
  "price_VSC_VN": {
    "updated": "2026-05-15T08:17:03.945337",
    "rows": 88,
    "start": "2025-12-30 00:00:00",
    "end": "2026-05-14 00:00:00"
  },
  "price_SDN_VN": {
    "updated": "2026-05-15T08:17:06.256036",
    "rows": 88,
    "start": "2025-06-17 00:00:00",
    "end": "2026-05-11 00:00:00"
  },
  "price_PMG_VN": {
    "updated": "2026-05-15T08:17:08.384226",
    "rows": 88,
    "start": "2025-12-18 00:00:00",
    "end": "2026-05-14 00:00:00"
  },
  "price_HAS_VN": {
    "updated": "2026-05-15T08:17:10.693569",
    "rows": 88,
    "start": "2025-07-29 00:00:00",
    "end": "2026-05-12 00:00:00"
  },
  "price_TVT_VN": {
    "updated": "2026-05-15T08:17:12.914107",
    "rows": 88,
    "start": "2025-12-15 00:00:00",
    "end": "2026-05-14 00:00:00"
  },
  "price_PSD_VN": {
    "updated": "2026-05-15T08:17:15.059215",
    "rows": 88,
    "start": "2025-12-30 00:00:00",
    "end": "2026-05-14 00:00:00"
  },
  "price_SHE_VN": {
    "updated": "2026-05-15T08:17:17.283259",
    "rows": 88,
    "start": "2025-12-23 00:00:00",
    "end": "2026-05-14 00:00:00"
  },
  "price_VMS_VN": {
    "updated": "2026-05-15T08:17:19.372118",
    "rows": 88,
    "start": "2025-06-16 00:00:00",
    "end": "2026-05-06 00:00:00"
  },
  "price_HTC_VN": {
    "updated": "2026-05-15T08:17:21.414867",
    "rows": 88,
    "start": "2025-12-29 00:00:00",
    "end": "2026-05-13 00:00:00"
  },
  "price_NAG_VN": {
    "updated": "2026-05-15T08:17:23.491907",
    "rows": 88,
    "start": "2025-12-30 00:00:00",
    "end": "2026-05-14 00:00:00"
  },
  "price_DTD_VN": {
    "updated": "2026-05-15T08:17:25.675564",
    "rows": 88,
    "start": "2025-12-30 00:00:00",
    "end": "2026-05-14 00:00:00"
  },
  "price_TBC_VN": {
    "updated": "2026-05-15T08:17:27.829319",
    "rows": 88,
    "start": "2025-12-29 00:00:00",
    "end": "2026-05-14 00:00:00"
  },
  "price_DAE_VN": {
    "updated": "2026-05-15T08:17:30.204176",
    "rows": 88,
    "start": "2025-11-04 00:00:00",
    "end": "2026-05-14 00:00:00"
  },
  "price_DHT_VN": {
    "updated": "2026-05-15T08:17:32.301815",
    "rows": 88,
    "start": "2025-12-30 00:00:00",
    "end": "2026-05-14 00:00:00"
  },
  "price_HID_VN": {
    "updated": "2026-05-15T08:17:34.414292",
    "rows": 88,
    "start": "2025-12-30 00:00:00",
    "end": "2026-05-14 00:00:00"
  },
  "price_V12_VN": {
    "updated": "2026-05-15T08:17:36.512195",
    "rows": 88,
    "start": "2025-07-11 00:00:00",
    "end": "2026-05-12 00:00:00"
  },
  "price_PTD_VN": {
    "updated": "2026-05-15T08:17:38.629445",
    "rows": 88,
    "start": "2025-05-07 00:00:00",
    "end": "2026-05-13 00:00:00"
  },
  "price_CHP_VN": {
    "updated": "2026-05-24T10:57:53.772376",
    "rows": 248,
    "start": "2025-05-26 00:00:00",
    "end": "2026-05-22 00:00:00"
  },
  "price_DMC_VN": {
    "updated": "2026-05-24T10:57:59.192060",
    "rows": 224,
    "start": "2025-05-26 00:00:00",
    "end": "2026-05-22 00:00:00"
  },
  "price_VC6_VN": {
    "updated": "2026-05-15T08:17:44.925618",
    "rows": 88,
    "start": "2025-11-27 00:00:00",
    "end": "2026-05-14 00:00:00"
  },
  "price_MCH_VN": {
    "updated": "2026-05-15T08:17:47.004922",
    "rows": 88,
    "start": "2025-12-30 00:00:00",
    "end": "2026-05-14 00:00:00"
  },
  "price_TV2_VN": {
    "updated": "2026-06-01T21:34:31.453213",
    "rows": 268,
    "start": "2025-05-06 00:00:00",
    "end": "2026-06-01 00:00:00"
  },
  "price_VTP_VN": {
    "updated": "2026-05-15T08:17:51.345740",
    "rows": 88,
    "start": "2025-12-30 00:00:00",
    "end": "2026-05-14 00:00:00"
  },
  "price_TTE_VN": {
    "updated": "2026-05-15T08:17:53.463006",
    "rows": 88,
    "start": "2024-07-04 00:00:00",
    "end": "2026-03-19 00:00:00"
  },
  "price_DHA_VN": {
    "updated": "2026-05-15T08:17:55.641846",
    "rows": 88,
    "start": "2025-12-30 00:00:00",
    "end": "2026-05-14 00:00:00"
  },
  "price_CCL_VN": {
    "updated": "2026-05-24T10:57:53.018572",
    "rows": 248,
    "start": "2025-05-26 00:00:00",
    "end": "2026-05-22 00:00:00"
  },
  "price_EBS_VN": {
    "updated": "2026-05-15T08:17:59.445622",
    "rows": 88,
    "start": "2025-11-18 00:00:00",
    "end": "2026-05-13 00:00:00"
  },
  "price_TIX_VN": {
    "updated": "2026-05-15T08:18:01.439195",
    "rows": 88,
    "start": "2025-09-04 00:00:00",
    "end": "2026-05-14 00:00:00"
  },
  "price_SHA_VN": {
    "updated": "2026-05-15T08:18:03.384789",
    "rows": 88,
    "start": "2025-12-26 00:00:00",
    "end": "2026-05-13 00:00:00"
  },
  "price_VNC_VN": {
    "updated": "2026-05-15T08:18:05.356517",
    "rows": 88,
    "start": "2025-12-30 00:00:00",
    "end": "2026-05-14 00:00:00"
  },
  "price_BTS_VN": {
    "updated": "2026-05-15T08:18:07.295610",
    "rows": 88,
    "start": "2025-12-23 00:00:00",
    "end": "2026-05-14 00:00:00"
  },
  "price_NHA_VN": {
    "updated": "2026-05-15T08:18:09.287303",
    "rows": 88,
    "start": "2025-12-30 00:00:00",
    "end": "2026-05-14 00:00:00"
  },
  "price_ANT_VN": {
    "updated": "2026-05-24T10:57:47.278361",
    "rows": 94,
    "start": "2025-12-23 00:00:00",
    "end": "2026-05-22 00:00:00"
  },
  "price_PGD_VN": {
    "updated": "2026-05-15T08:18:13.154682",
    "rows": 88,
    "start": "2025-12-30 00:00:00",
    "end": "2026-05-14 00:00:00"
  },
  "price_PSW_VN": {
    "updated": "2026-05-15T08:18:15.118675",
    "rows": 88,
    "start": "2025-12-30 00:00:00",
    "end": "2026-05-14 00:00:00"
  },
  "price_HNA_VN": {
    "updated": "2026-05-15T08:18:17.128199",
    "rows": 88,
    "start": "2025-12-15 00:00:00",
    "end": "2026-05-14 00:00:00"
  },
  "price_DNP_VN": {
    "updated": "2026-05-15T08:18:19.106315",
    "rows": 88,
    "start": "2025-11-05 00:00:00",
    "end": "2026-05-14 00:00:00"
  },
  "price_CAP_VN": {
    "updated": "2026-05-15T08:18:21.025114",
    "rows": 88,
    "start": "2025-12-30 00:00:00",
    "end": "2026-05-14 00:00:00"
  },
  "price_TCX_VN": {
    "updated": "2026-05-15T08:18:23.006309",
    "rows": 88,
    "start": "2025-12-30 00:00:00",
    "end": "2026-05-14 00:00:00"
  },
  "price_UIC_VN": {
    "updated": "2026-05-15T08:18:25.024611",
    "rows": 88,
    "start": "2025-12-04 00:00:00",
    "end": "2026-05-13 00:00:00"
  },
  "price_NDN_VN": {
    "updated": "2026-05-15T08:18:27.051731",
    "rows": 88,
    "start": "2025-12-30 00:00:00",
    "end": "2026-05-14 00:00:00"
  },
  "price_SVC_VN": {
    "updated": "2026-05-15T08:18:29.081827",
    "rows": 88,
    "start": "2025-12-26 00:00:00",
    "end": "2026-05-14 00:00:00"
  },
  "price_CIA_VN": {
    "updated": "2026-05-15T08:18:30.952006",
    "rows": 88,
    "start": "2025-12-16 00:00:00",
    "end": "2026-05-13 00:00:00"
  },
  "price_CSC_VN": {
    "updated": "2026-05-15T08:18:32.883896",
    "rows": 88,
    "start": "2025-12-30 00:00:00",
    "end": "2026-05-14 00:00:00"
  },
  "price_TCM_VN": {
    "updated": "2026-05-15T08:18:34.924204",
    "rows": 88,
    "start": "2025-12-30 00:00:00",
    "end": "2026-05-14 00:00:00"
  },
  "price_VPD_VN": {
    "updated": "2026-05-15T08:18:36.886900",
    "rows": 88,
    "start": "2025-12-29 00:00:00",
    "end": "2026-05-14 00:00:00"
  },
  "price_BNA_VN": {
    "updated": "2026-05-15T08:18:38.859338",
    "rows": 88,
    "start": "2025-12-30 00:00:00",
    "end": "2026-05-14 00:00:00"
  },
  "price_BMI_VN": {
    "updated": "2026-05-24T10:57:50.270859",
    "rows": 248,
    "start": "2025-05-26 00:00:00",
    "end": "2026-05-22 00:00:00"
  },
  "price_HGM_VN": {
    "updated": "2026-05-15T08:18:43.129432",
    "rows": 88,
    "start": "2025-12-30 00:00:00",
    "end": "2026-05-14 00:00:00"
  },
  "price_HDG_VN": {
    "updated": "2026-06-01T21:22:13.549092",
    "rows": 268,
    "start": "2025-05-06 00:00:00",
    "end": "2026-06-01 00:00:00"
  },
  "price_KSV_VN": {
    "updated": "2026-05-15T08:18:46.931619",
    "rows": 88,
    "start": "2025-12-30 00:00:00",
    "end": "2026-05-14 00:00:00"
  },
  "price_VGS_VN": {
    "updated": "2026-05-15T08:20:01.532052",
    "rows": 155,
    "start": "2025-08-19 00:00:00",
    "end": "2026-05-14 00:00:00"
  },
  "price_IDC_VN": {
    "updated": "2026-05-15T08:20:03.418402",
    "rows": 155,
    "start": "2025-08-19 00:00:00",
    "end": "2026-05-14 00:00:00"
  },
  "price_AAA_VN": {
    "updated": "2026-06-01T21:25:52.077261",
    "rows": 268,
    "start": "2025-05-06 00:00:00",
    "end": "2026-06-01 00:00:00"
  },
  "price_AAM_VN": {
    "updated": "2026-05-24T10:58:02.182998",
    "rows": 262,
    "start": "2025-04-25 00:00:00",
    "end": "2026-05-22 00:00:00"
  },
  "price_AAN_VN": {
    "updated": "2026-05-24T10:57:44.855651",
    "rows": 1,
    "start": "2026-05-22 00:00:00",
    "end": "2026-05-22 00:00:00"
  },
  "price_AAT_VN": {
    "updated": "2026-05-24T10:57:44.856361",
    "rows": 262,
    "start": "2025-05-06 00:00:00",
    "end": "2026-05-22 00:00:00"
  },
  "price_ABR_VN": {
    "updated": "2026-05-24T10:58:02.179457",
    "rows": 262,
    "start": "2025-04-02 00:00:00",
    "end": "2026-05-22 00:00:00"
  },
  "price_ABS_VN": {
    "updated": "2026-05-24T10:58:02.181975",
    "rows": 262,
    "start": "2025-05-06 00:00:00",
    "end": "2026-05-22 00:00:00"
  },
  "price_ABT_VN": {
    "updated": "2026-05-24T10:57:46.032262",
    "rows": 262,
    "start": "2025-05-06 00:00:00",
    "end": "2026-05-22 00:00:00"
  },
  "price_ACC_VN": {
    "updated": "2026-05-24T10:58:05.543751",
    "rows": 262,
    "start": "2025-04-23 00:00:00",
    "end": "2026-05-22 00:00:00"
  },
  "price_ACG_VN": {
    "updated": "2026-05-24T10:58:05.550553",
    "rows": 262,
    "start": "2025-05-05 00:00:00",
    "end": "2026-05-22 00:00:00"
  },
  "price_ACL_VN": {
    "updated": "2026-05-24T10:58:06.781256",
    "rows": 241,
    "start": "2025-05-26 00:00:00",
    "end": "2026-05-21 00:00:00"
  },
  "price_ADG_VN": {
    "updated": "2026-05-24T10:58:07.232031",
    "rows": 238,
    "start": "2025-05-26 00:00:00",
    "end": "2026-05-22 00:00:00"
  },
  "price_ADS_VN": {
    "updated": "2026-05-24T10:58:08.175716",
    "rows": 248,
    "start": "2025-05-26 00:00:00",
    "end": "2026-05-22 00:00:00"
  },
  "price_ADP_VN": {
    "updated": "2026-05-24T10:58:07.313692",
    "rows": 260,
    "start": "2025-05-26 00:00:00",
    "end": "2026-05-22 00:00:00"
  },
  "price_AFX_VN": {
    "updated": "2026-05-24T10:58:08.824659",
    "rows": 110,
    "start": "2025-12-08 00:00:00",
    "end": "2026-05-22 00:00:00"
  },
  "price_APG_VN": {
    "updated": "2026-05-24T10:57:47.309071",
    "rows": 248,
    "start": "2025-05-26 00:00:00",
    "end": "2026-05-22 00:00:00"
  },
  "price_APH_VN": {
    "updated": "2026-05-24T10:57:47.354319",
    "rows": 248,
    "start": "2025-05-26 00:00:00",
    "end": "2026-05-22 00:00:00"
  },
  "price_ASG_VN": {
    "updated": "2026-05-24T10:58:09.879173",
    "rows": 173,
    "start": "2025-05-26 00:00:00",
    "end": "2026-05-19 00:00:00"
  },
  "price_ASP_VN": {
    "updated": "2026-05-26T22:34:58.195565",
    "rows": 343,
    "start": "2025-01-02 00:00:00",
    "end": "2026-05-26 00:00:00"
  },
  "price_AST_VN": {
    "updated": "2026-05-24T10:58:11.338301",
    "rows": 246,
    "start": "2025-05-26 00:00:00",
    "end": "2026-05-22 00:00:00"
  },
  "price_BAF_VN": {
    "updated": "2026-05-26T22:33:15.863638",
    "rows": 367,
    "start": "2024-11-28 00:00:00",
    "end": "2026-05-26 00:00:00"
  },
  "price_BCE_VN": {
    "updated": "2026-05-24T10:58:12.989607",
    "rows": 248,
    "start": "2025-05-26 00:00:00",
    "end": "2026-05-22 00:00:00"
  },
  "price_BCG_VN": {
    "updated": "2026-05-24T10:58:13.660176",
    "rows": 260,
    "start": "2025-05-26 00:00:00",
    "end": "2026-05-22 00:00:00"
  },
  "price_BIC_VN": {
    "updated": "2026-05-24T10:58:15.000733",
    "rows": 248,
    "start": "2025-05-26 00:00:00",
    "end": "2026-05-22 00:00:00"
  },
  "price_BFC_VN": {
    "updated": "2026-05-24T10:58:13.815536",
    "rows": 248,
    "start": "2025-05-26 00:00:00",
    "end": "2026-05-22 00:00:00"
  },
  "price_BHN_VN": {
    "updated": "2026-06-01T21:30:04.754323",
    "rows": 244,
    "start": "2025-05-26 00:00:00",
    "end": "2026-06-01 00:00:00"
  },
  "price_BKG_VN": {
    "updated": "2026-05-24T10:57:49.875698",
    "rows": 248,
    "start": "2025-05-26 00:00:00",
    "end": "2026-05-22 00:00:00"
  },
  "price_BMC_VN": {
    "updated": "2026-05-24T10:57:49.888572",
    "rows": 248,
    "start": "2025-05-26 00:00:00",
    "end": "2026-05-22 00:00:00"
  },
  "price_BRC_VN": {
    "updated": "2026-05-24T10:58:16.228100",
    "rows": 223,
    "start": "2025-05-26 00:00:00",
    "end": "2026-05-20 00:00:00"
  },
  "price_BTP_VN": {
    "updated": "2026-05-24T10:58:17.726692",
    "rows": 248,
    "start": "2025-05-26 00:00:00",
    "end": "2026-05-22 00:00:00"
  },
  "price_BTT_VN": {
    "updated": "2026-05-24T10:58:18.841224",
    "rows": 260,
    "start": "2025-05-26 00:00:00",
    "end": "2026-05-22 00:00:00"
  },
  "price_C32_VN": {
    "updated": "2026-05-24T10:57:51.542290",
    "rows": 239,
    "start": "2025-05-27 00:00:00",
    "end": "2026-05-22 00:00:00"
  },
  "price_BWE_VN": {
    "updated": "2026-06-01T21:26:50.158381",
    "rows": 21,
    "start": "2026-05-04 00:00:00",
    "end": "2026-06-01 00:00:00"
  },
  "price_C47_VN": {
    "updated": "2026-05-24T10:57:51.899804",
    "rows": 248,
    "start": "2025-05-26 00:00:00",
    "end": "2026-05-22 00:00:00"
  },
  "price_CCC_VN": {
    "updated": "2026-05-24T10:57:52.674818",
    "rows": 260,
    "start": "2025-05-26 00:00:00",
    "end": "2026-05-22 00:00:00"
  },
  "price_CCI_VN": {
    "updated": "2026-05-24T10:57:53.020329",
    "rows": 171,
    "start": "2025-05-27 00:00:00",
    "end": "2026-05-21 00:00:00"
  },
  "price_CIG_VN": {
    "updated": "2026-05-24T10:57:53.846473",
    "rows": 248,
    "start": "2025-05-26 00:00:00",
    "end": "2026-05-22 00:00:00"
  },
  "price_CKG_VN": {
    "updated": "2026-05-24T10:57:53.909850",
    "rows": 248,
    "start": "2025-05-26 00:00:00",
    "end": "2026-05-22 00:00:00"
  },
  "price_CLC_VN": {
    "updated": "2026-05-24T10:57:54.200259",
    "rows": 208,
    "start": "2025-05-26 00:00:00",
    "end": "2026-05-22 00:00:00"
  },
  "price_CLL_VN": {
    "updated": "2026-05-24T10:57:54.536318",
    "rows": 247,
    "start": "2025-05-26 00:00:00",
    "end": "2026-05-22 00:00:00"
  },
  "price_CLW_VN": {
    "updated": "2026-05-24T10:57:54.935255",
    "rows": 260,
    "start": "2025-05-26 00:00:00",
    "end": "2026-05-22 00:00:00"
  },
  "price_CMX_VN": {
    "updated": "2026-05-24T10:57:55.278952",
    "rows": 248,
    "start": "2025-05-26 00:00:00",
    "end": "2026-05-22 00:00:00"
  },
  "price_CMV_VN": {
    "updated": "2026-05-24T10:57:55.281187",
    "rows": 171,
    "start": "2025-05-26 00:00:00",
    "end": "2026-05-22 00:00:00"
  },
  "price_CNG_VN": {
    "updated": "2026-05-24T10:57:55.654128",
    "rows": 248,
    "start": "2025-05-26 00:00:00",
    "end": "2026-05-22 00:00:00"
  },
  "price_COM_VN": {
    "updated": "2026-05-24T10:57:55.656787",
    "rows": 117,
    "start": "2025-05-26 00:00:00",
    "end": "2026-05-13 00:00:00"
  },
  "price_CRV_VN": {
    "updated": "2026-05-24T10:57:56.017450",
    "rows": 125,
    "start": "2025-10-10 00:00:00",
    "end": "2026-05-18 00:00:00"
  },
  "price_CRE_VN": {
    "updated": "2026-05-24T10:57:56.019931",
    "rows": 248,
    "start": "2025-05-26 00:00:00",
    "end": "2026-05-22 00:00:00"
  },
  "price_CRC_VN": {
    "updated": "2026-05-24T10:57:56.020979",
    "rows": 248,
    "start": "2025-05-26 00:00:00",
    "end": "2026-05-22 00:00:00"
  },
  "price_CSM_VN": {
    "updated": "2026-05-24T10:57:56.179710",
    "rows": 248,
    "start": "2025-05-26 00:00:00",
    "end": "2026-05-22 00:00:00"
  },
  "price_CSV_VN": {
    "updated": "2026-06-01T21:29:59.333598",
    "rows": 268,
    "start": "2025-05-06 00:00:00",
    "end": "2026-06-01 00:00:00"
  },
  "price_CTD_VN": {
    "updated": "2026-06-01T21:32:33.915649",
    "rows": 159,
    "start": "2025-10-08 00:00:00",
    "end": "2026-06-01 00:00:00"
  },
  "price_CTI_VN": {
    "updated": "2026-05-24T10:57:56.868661",
    "rows": 248,
    "start": "2025-05-26 00:00:00",
    "end": "2026-05-22 00:00:00"
  },
  "price_CTR_VN": {
    "updated": "2026-05-24T10:57:57.016883",
    "rows": 248,
    "start": "2025-05-26 00:00:00",
    "end": "2026-05-22 00:00:00"
  },
  "price_CVT_VN": {
    "updated": "2026-05-24T10:57:57.291443",
    "rows": 142,
    "start": "2025-05-26 00:00:00",
    "end": "2026-05-19 00:00:00"
  },
  "price_CTS_VN": {
    "updated": "2026-06-01T21:32:04.910210",
    "rows": 268,
    "start": "2025-05-06 00:00:00",
    "end": "2026-06-01 00:00:00"
  },
  "price_D2D_VN": {
    "updated": "2026-05-24T10:57:57.650290",
    "rows": 248,
    "start": "2025-05-26 00:00:00",
    "end": "2026-05-22 00:00:00"
  },
  "price_DAH_VN": {
    "updated": "2026-05-24T10:57:58.004287",
    "rows": 248,
    "start": "2025-05-26 00:00:00",
    "end": "2026-05-22 00:00:00"
  },
  "price_DAT_VN": {
    "updated": "2026-05-24T10:57:58.463283",
    "rows": 225,
    "start": "2025-05-26 00:00:00",
    "end": "2026-05-22 00:00:00"
  },
  "price_DBC_VN": {
    "updated": "2026-06-01T21:28:56.769963",
    "rows": 21,
    "start": "2026-05-04 00:00:00",
    "end": "2026-06-01 00:00:00"
  },
  "price_DBD_VN": {
    "updated": "2026-05-24T10:57:58.569595",
    "rows": 248,
    "start": "2025-05-26 00:00:00",
    "end": "2026-05-22 00:00:00"
  },
  "price_DBT_VN": {
    "updated": "2026-05-24T10:57:58.626231",
    "rows": 225,
    "start": "2025-05-26 00:00:00",
    "end": "2026-05-22 00:00:00"
  },
  "price_DC4_VN": {
    "updated": "2026-05-24T10:57:58.631266",
    "rows": 248,
    "start": "2025-05-26 00:00:00",
    "end": "2026-05-22 00:00:00"
  },
  "price_DCL_VN": {
    "updated": "2026-05-24T10:57:59.178278",
    "rows": 248,
    "start": "2025-05-26 00:00:00",
    "end": "2026-05-22 00:00:00"
  },
  "fundamentals_HPG_VN": {
    "updated": "2026-06-01T21:24:10.672852"
  },
  "fundamentals_VCB_VN": {
    "updated": "2026-06-01T21:15:17.107227"
  },
  "fundamentals_BID_VN": {
    "updated": "2026-06-01T21:16:45.246651"
  },
  "fundamentals_CTG_VN": {
    "updated": "2026-06-01T21:16:55.726439"
  },
  "fundamentals_TCB_VN": {
    "updated": "2026-06-01T21:17:07.061702"
  },
  "fundamentals_MBB_VN": {
    "updated": "2026-06-01T21:17:17.284083"
  },
  "fundamentals_ACB_VN": {
    "updated": "2026-06-01T21:17:29.496270"
  },
  "fundamentals_VPB_VN": {
    "updated": "2026-06-01T21:17:39.600362"
  },
  "fundamentals_STB_VN": {
    "updated": "2026-06-01T21:17:49.457279"
  },
  "fundamentals_HDB_VN": {
    "updated": "2026-06-01T21:17:59.925913"
  },
  "fundamentals_LPB_VN": {
    "updated": "2026-06-01T21:18:11.398144"
  },
  "fundamentals_SSB_VN": {
    "updated": "2026-06-01T21:18:29.224547"
  },
  "fundamentals_EIB_VN": {
    "updated": "2026-06-01T21:18:39.614848"
  },
  "fundamentals_OCB_VN": {
    "updated": "2026-06-01T21:18:49.022378"
  },
  "fundamentals_TPB_VN": {
    "updated": "2026-06-01T21:18:58.157863"
  },
  "fundamentals_SHB_VN": {
    "updated": "2026-06-01T21:19:17.561549"
  },
  "fundamentals_EVF_VN": {
    "updated": "2026-06-01T21:19:27.655927"
  },
  "fundamentals_VIC_VN": {
    "updated": "2026-06-01T21:19:34.897041"
  },
  "fundamentals_VHM_VN": {
    "updated": "2026-06-01T21:19:44.483358"
  },
  "fundamentals_VRE_VN": {
    "updated": "2026-06-01T21:19:53.868582"
  },
  "fundamentals_KDH_VN": {
    "updated": "2026-06-01T21:20:03.317606"
  },
  "fundamentals_NVL_VN": {
    "updated": "2026-06-01T21:20:10.865576"
  },
  "fundamentals_PDR_VN": {
    "updated": "2026-06-01T21:20:18.585459"
  },
  "fundamentals_DXG_VN": {
    "updated": "2026-06-01T21:20:26.130171"
  },
  "fundamentals_IJC_VN": {
    "updated": "2026-06-01T21:20:35.647279"
  },
  "fundamentals_SIP_VN": {
    "updated": "2026-06-01T21:20:52.064770"
  },
  "fundamentals_HDC_VN": {
    "updated": "2026-06-01T21:20:59.372772"
  },
  "fundamentals_HAG_VN": {
    "updated": "2026-06-01T21:21:06.647236"
  },
  "fundamentals_LCG_VN": {
    "updated": "2026-06-01T21:21:16.587658"
  },
  "fundamentals_VPI_VN": {
    "updated": "2026-06-01T21:21:23.942307"
  },
  "fundamentals_CII_VN": {
    "updated": "2026-06-01T21:21:33.385956"
  },
  "fundamentals_HDG_VN": {
    "updated": "2026-06-01T21:21:55.121962"
  },
  "fundamentals_PC1_VN": {
    "updated": "2026-06-01T21:22:23.671780"
  },
  "fundamentals_VCG_VN": {
    "updated": "2026-06-01T21:22:45.739195"
  },
  "fundamentals_GAS_VN": {
    "updated": "2026-06-01T21:24:01.079032"
  },
  "fundamentals_PLX_VN": {
    "updated": "2026-06-01T21:24:23.748304"
  },
  "fundamentals_GVR_VN": {
    "updated": "2026-06-01T21:24:34.571975"
  },
  "fundamentals_BSR_VN": {
    "updated": "2026-06-01T21:24:44.497019"
  },
  "fundamentals_DGC_VN": {
    "updated": "2026-06-01T21:24:54.203376"
  },
  "fundamentals_PHR_VN": {
    "updated": "2026-06-01T21:25:01.647954"
  },
  "fundamentals_DPR_VN": {
    "updated": "2026-06-01T21:25:09.343602"
  },
  "fundamentals_TRC_VN": {
    "updated": "2026-06-01T21:25:30.750420"
  },
  "fundamentals_BMP_VN": {
    "updated": "2026-06-01T21:25:41.285735"
  },
  "fundamentals_AAA_VN": {
    "updated": "2026-06-01T21:25:48.886727"
  },
  "fundamentals_LSS_VN": {
    "updated": "2026-06-01T21:25:59.000262"
  },
  "fundamentals_PPC_VN": {
    "updated": "2026-06-01T21:26:08.522563"
  },
  "fundamentals_NT2_VN": {
    "updated": "2026-06-01T21:26:17.522632"
  },
  "fundamentals_POW_VN": {
    "updated": "2026-06-01T21:26:27.801435"
  },
  "fundamentals_GEG_VN": {
    "updated": "2026-06-01T21:26:37.591804"
  },
  "fundamentals_BWE_VN": {
    "updated": "2026-06-01T21:26:47.122939"
  },
  "fundamentals_KHP_VN": {
    "updated": "2026-06-01T21:26:56.940646"
  },
  "fundamentals_REE_VN": {
    "updated": "2026-06-01T21:27:06.470692"
  },
  "fundamentals_GEX_VN": {
    "updated": "2026-06-01T21:27:13.883336"
  },
  "fundamentals_HHV_VN": {
    "updated": "2026-06-01T21:27:21.091203"
  },
  "fundamentals_PVT_VN": {
    "updated": "2026-06-01T21:23:48.681214"
  },
  "fundamentals_SAB_VN": {
    "updated": "2026-06-01T21:27:45.069988"
  },
  "fundamentals_MSN_VN": {
    "updated": "2026-06-01T21:27:54.693861"
  },
  "fundamentals_VNM_VN": {
    "updated": "2026-06-01T21:28:04.879191"
  },
  "fundamentals_MWG_VN": {
    "updated": "2026-06-01T21:28:16.663882"
  },
  "fundamentals_PNJ_VN": {
    "updated": "2026-06-01T21:28:27.610833"
  },
  "fundamentals_TLG_VN": {
    "updated": "2026-06-01T21:28:37.456237"
  },
  "fundamentals_DHC_VN": {
    "updated": "2026-06-01T21:28:44.512295"
  },
  "fundamentals_DBC_VN": {
    "updated": "2026-06-01T21:28:53.857364"
  },
  "fundamentals_PAN_VN": {
    "updated": "2026-06-01T21:29:03.254513"
  },
  "fundamentals_VHC_VN": {
    "updated": "2026-06-01T21:29:13.154207"
  },
  "fundamentals_HAX_VN": {
    "updated": "2026-06-01T21:29:20.700961"
  },
  "fundamentals_HAH_VN": {
    "updated": "2026-06-01T21:29:30.465412"
  },
  "fundamentals_VTO_VN": {
    "updated": "2026-06-01T21:29:39.723004"
  },
  "fundamentals_ASM_VN": {
    "updated": "2026-06-01T21:29:49.129586"
  },
  "fundamentals_CSV_VN": {
    "updated": "2026-06-01T21:29:56.273555"
  },
  "fundamentals_FPT_VN": {
    "updated": "2026-06-01T21:30:11.528505"
  },
  "fundamentals_CMG_VN": {
    "updated": "2026-06-01T21:30:23.632776"
  },
  "fundamentals_VNE_VN": {
    "updated": "2026-06-01T21:30:31.678639"
  },
  "fundamentals_VJC_VN": {
    "updated": "2026-06-01T21:30:45.800568"
  },
  "fundamentals_GMD_VN": {
    "updated": "2026-06-01T21:30:55.677724"
  },
  "fundamentals_SSI_VN": {
    "updated": "2026-06-01T21:31:07.944721"
  },
  "fundamentals_VCI_VN": {
    "updated": "2026-06-01T21:31:17.814016"
  },
  "fundamentals_HCM_VN": {
    "updated": "2026-06-01T21:31:25.716571"
  },
  "fundamentals_VND_VN": {
    "updated": "2026-06-01T21:31:35.429867"
  },
  "fundamentals_BSI_VN": {
    "updated": "2026-06-01T21:31:44.995342"
  },
  "fundamentals_ORS_VN": {
    "updated": "2026-06-01T21:31:52.285587"
  },
  "fundamentals_CTS_VN": {
    "updated": "2026-06-01T21:32:01.929443"
  },
  "fundamentals_FTS_VN": {
    "updated": "2026-06-01T21:32:11.571191"
  },
  "fundamentals_VDS_VN": {
    "updated": "2026-06-01T21:32:21.787388"
  },
  "fundamentals_CTD_VN": {
    "updated": "2026-06-01T21:32:30.559192"
  },
  "fundamentals_FCN_VN": {
    "updated": "2026-06-01T21:32:40.473337"
  },
  "fundamentals_AGR_VN": {
    "updated": "2026-06-01T21:32:52.065530"
  },
  "fundamentals_DPM_VN": {
    "updated": "2026-06-01T21:32:59.478420"
  },
  "fundamentals_DCM_VN": {
    "updated": "2026-06-01T21:33:09.523834"
  },
  "fundamentals_BVH_VN": {
    "updated": "2026-06-01T21:33:43.297127"
  },
  "fundamentals_BCM_VN": {
    "updated": "2026-06-01T21:33:53.040402"
  },
  "fundamentals_SCS_VN": {
    "updated": "2026-06-01T21:34:03.007202"
  },
  "fundamentals_TDM_VN": {
    "updated": "2026-06-01T21:34:20.263497"
  },
  "fundamentals_TV2_VN": {
    "updated": "2026-06-01T21:34:28.340182"
  },
  "fundamentals_8096.TWO_TW": {
    "updated": "2026-05-25T20:08:40.824380"
  },
  "fundamentals_2330.TW_TW": {
    "updated": "2026-05-25T20:08:52.027601"
  },
  "fundamentals_2454.TW_TW": {
    "updated": "2026-05-25T20:08:54.306874"
  },
  "fundamentals_2317.TW_TW": {
    "updated": "2026-05-25T20:08:56.589235"
  },
  "fundamentals_2382.TW_TW": {
    "updated": "2026-05-25T20:08:58.871370"
  },
  "fundamentals_PVS_VN": {
    "updated": "2026-05-26T19:39:00.963679"
  },
  "fundamentals_PVD_VN": {
    "updated": "2026-05-26T19:39:10.649004"
  },
  "fundamentals_PVB_VN": {
    "updated": "2026-05-26T19:39:20.066130"
  },
  "fundamentals_PVI_VN": {
    "updated": "2026-05-26T19:39:30.286514"
  },
  "fundamentals_NKG_VN": {
    "updated": "2026-05-26T19:39:39.793933"
  },
  "fundamentals_TLH_VN": {
    "updated": "2026-05-26T19:39:49.480190"
  },
  "fundamentals_SMC_VN": {
    "updated": "2026-05-26T19:39:59.226277"
  },
  "fundamentals_HSG_VN": {
    "updated": "2026-05-26T19:40:08.529432"
  },
  "fundamentals_HVN_VN": {
    "updated": "2026-05-26T19:40:17.776209"
  },
  "fundamentals_DHG_VN": {
    "updated": "2026-05-26T19:40:26.894578"
  },
  "fundamentals_IMP_VN": {
    "updated": "2026-05-26T19:40:36.061858"
  },
  "fundamentals_NLG_VN": {
    "updated": "2026-05-26T19:40:45.387176"
  },
  "fundamentals_MBS_VN": {
    "updated": "2026-05-26T19:40:54.773897"
  },
  "fundamentals_HBC_VN": {
    "updated": "2026-05-26T19:41:04.371863"
  },
  "fundamentals_SZC_VN": {
    "updated": "2026-05-26T20:01:53.861598"
  },
  "fundamentals_BHN_VN": {
    "updated": "2026-05-26T20:02:49.278314"
  },
  "fundamentals_SGT_VN": {
    "updated": "2026-05-26T20:02:59.006056"
  },
  "fundamentals_TRA_VN": {
    "updated": "2026-05-26T20:03:29.370147"
  },
  "fundamentals_VGC_VN": {
    "updated": "2026-05-26T20:03:41.595951"
  },
  "fundamentals_2303.TW_TW": {
    "updated": "2026-05-26T20:35:13.715033"
  },
  "fundamentals_3711.TW_TW": {
    "updated": "2026-05-26T20:35:15.207793"
  },
  "fundamentals_3034.TW_TW": {
    "updated": "2026-05-26T20:35:16.821902"
  },
  "fundamentals_2379.TW_TW": {
    "updated": "2026-05-26T20:35:18.460037"
  },
  "fundamentals_4919.TW_TW": {
    "updated": "2026-05-26T20:35:20.137230"
  },
  "fundamentals_5274.TWO_TW": {
    "updated": "2026-05-26T20:35:21.677122"
  },
  "fundamentals_3661.TW_TW": {
    "updated": "2026-05-26T20:35:23.142813"
  },
  "fundamentals_3443.TW_TW": {
    "updated": "2026-05-26T20:35:24.617408"
  },
  "fundamentals_3035.TW_TW": {
    "updated": "2026-05-26T20:35:26.152310"
  },
  "fundamentals_5269.TW_TW": {
    "updated": "2026-05-26T20:35:27.687448"
  },
  "fundamentals_6415.TW_TW": {
    "updated": "2026-05-26T20:35:29.226383"
  },
  "fundamentals_5347.TWO_TW": {
    "updated": "2026-05-26T20:35:30.810596"
  },
  "fundamentals_2408.TW_TW": {
    "updated": "2026-05-26T20:35:32.405790"
  },
  "fundamentals_2337.TW_TW": {
    "updated": "2026-05-26T20:35:34.274249"
  },
  "fundamentals_2344.TW_TW": {
    "updated": "2026-05-26T20:35:35.782136"
  },
  "fundamentals_8299.TWO_TW": {
    "updated": "2026-05-26T20:35:37.350668"
  },
  "fundamentals_3036.TW_TW": {
    "updated": "2026-05-26T20:35:39.904759"
  },
  "fundamentals_3209.TW_TW": {
    "updated": "2026-05-26T20:35:41.445575"
  },
  "fundamentals_3702.TW_TW": {
    "updated": "2026-05-26T20:35:42.923121"
  },
  "fundamentals_6488.TWO_TW": {
    "updated": "2026-05-26T20:35:44.427618"
  },
  "fundamentals_3231.TW_TW": {
    "updated": "2026-05-26T20:35:48.583741"
  },
  "fundamentals_6669.TW_TW": {
    "updated": "2026-05-26T20:35:50.078787"
  },
  "fundamentals_2376.TW_TW": {
    "updated": "2026-05-26T20:35:51.637468"
  },
  "fundamentals_2357.TW_TW": {
    "updated": "2026-05-26T20:35:53.275270"
  },
  "fundamentals_2353.TW_TW": {
    "updated": "2026-05-26T20:35:54.811897"
  },
  "fundamentals_2324.TW_TW": {
    "updated": "2026-05-26T20:35:56.385989"
  },
  "fundamentals_2356.TW_TW": {
    "updated": "2026-05-26T20:35:57.961815"
  },
  "fundamentals_4938.TW_TW": {
    "updated": "2026-05-26T20:35:59.595116"
  },
  "fundamentals_2395.TW_TW": {
    "updated": "2026-05-26T20:36:01.152180"
  },
  "fundamentals_2377.TW_TW": {
    "updated": "2026-05-26T20:36:02.752001"
  },
  "fundamentals_3017.TW_TW": {
    "updated": "2026-05-26T20:36:04.277750"
  },
  "fundamentals_3653.TW_TW": {
    "updated": "2026-05-26T20:36:06.005704"
  },
  "fundamentals_3037.TW_TW": {
    "updated": "2026-05-26T20:36:07.608569"
  },
  "fundamentals_8046.TW_TW": {
    "updated": "2026-05-26T20:36:09.224448"
  },
  "fundamentals_2368.TW_TW": {
    "updated": "2026-05-26T20:36:10.943367"
  },
  "fundamentals_2313.TW_TW": {
    "updated": "2026-05-26T20:36:12.506263"
  },
  "fundamentals_2383.TW_TW": {
    "updated": "2026-05-26T20:36:14.181394"
  },
  "fundamentals_6213.TW_TW": {
    "updated": "2026-05-26T20:36:15.736923"
  },
  "fundamentals_2308.TW_TW": {
    "updated": "2026-05-26T20:36:17.394189"
  },
  "fundamentals_2301.TW_TW": {
    "updated": "2026-05-26T20:36:18.953240"
  },
  "fundamentals_2449.TW_TW": {
    "updated": "2026-05-26T20:36:20.686209"
  },
  "fundamentals_3008.TW_TW": {
    "updated": "2026-05-26T20:36:22.297808"
  },
  "fundamentals_3406.TW_TW": {
    "updated": "2026-05-26T20:36:23.864065"
  },
  "fundamentals_4908.TWO_TW": {
    "updated": "2026-05-26T20:36:25.430962"
  },
  "fundamentals_2345.TW_TW": {
    "updated": "2026-05-26T20:36:26.926536"
  },
  "fundamentals_3533.TW_TW": {
    "updated": "2026-05-26T20:36:28.482337"
  },
  "fundamentals_2881.TW_TW": {
    "updated": "2026-05-26T20:36:30.011459"
  },
  "fundamentals_2882.TW_TW": {
    "updated": "2026-05-26T20:36:31.585406"
  },
  "fundamentals_2891.TW_TW": {
    "updated": "2026-05-26T20:36:33.195826"
  },
  "fundamentals_2886.TW_TW": {
    "updated": "2026-05-26T20:36:34.784383"
  },
  "fundamentals_2884.TW_TW": {
    "updated": "2026-05-26T20:36:36.299738"
  },
  "fundamentals_5880.TW_TW": {
    "updated": "2026-05-26T20:36:37.961016"
  },
  "fundamentals_2885.TW_TW": {
    "updated": "2026-05-26T20:36:39.630713"
  },
  "fundamentals_2002.TW_TW": {
    "updated": "2026-05-26T20:36:41.397443"
  },
  "fundamentals_1101.TW_TW": {
    "updated": "2026-05-26T20:36:42.968217"
  },
  "fundamentals_1303.TW_TW": {
    "updated": "2026-05-26T20:36:44.529590"
  },
  "fundamentals_1301.TW_TW": {
    "updated": "2026-05-26T20:36:46.218758"
  },
  "fundamentals_2327.TW_TW": {
    "updated": "2026-05-26T20:36:47.807360"
  },
  "fundamentals_2409.TW_TW": {
    "updated": "2026-05-26T20:36:49.438133"
  },
  "fundamentals_3481.TW_TW": {
    "updated": "2026-05-26T20:36:51.006143"
  },
  "fundamentals_8069.TWO_TW": {
    "updated": "2026-05-26T20:36:52.670367"
  },
  "fundamentals_2603.TW_TW": {
    "updated": "2026-05-26T20:36:54.353159"
  },
  "fundamentals_2609.TW_TW": {
    "updated": "2026-05-26T20:36:56.036067"
  },
  "fundamentals_2615.TW_TW": {
    "updated": "2026-05-26T20:36:57.725368"
  },
  "fundamentals_2618.TW_TW": {
    "updated": "2026-05-26T20:36:59.309050"
  },
  "fundamentals_1216.TW_TW": {
    "updated": "2026-05-26T20:37:00.877863"
  },
  "fundamentals_2412.TW_TW": {
    "updated": "2026-05-26T20:37:02.583988"
  },
  "fundamentals_3045.TW_TW": {
    "updated": "2026-05-26T20:37:04.123129"
  },
  "fundamentals_2912.TW_TW": {
    "updated": "2026-05-26T20:37:05.680214"
  },
  "price_VIX_VN": {
    "updated": "2026-05-26T21:49:10.729744",
    "rows": 249,
    "start": "2025-05-26 00:00:00",
    "end": "2026-05-25 00:00:00"
  },
  "price_VIP_VN": {
    "updated": "2026-05-26T21:49:10.781973",
    "rows": 249,
    "start": "2025-05-26 00:00:00",
    "end": "2026-05-25 00:00:00"
  },
  "price_VND_VN": {
    "updated": "2026-06-01T21:31:38.438615",
    "rows": 268,
    "start": "2025-05-06 00:00:00",
    "end": "2026-06-01 00:00:00"
  },
  "price_VTO_VN": {
    "updated": "2026-06-01T21:29:42.759265",
    "rows": 21,
    "start": "2026-05-04 00:00:00",
    "end": "2026-06-01 00:00:00"
  },
  "price_VOS_VN": {
    "updated": "2026-05-26T21:49:10.856755",
    "rows": 249,
    "start": "2025-05-26 00:00:00",
    "end": "2026-05-25 00:00:00"
  },
  "fundamentals_ASP_VN": {
    "updated": "2026-05-26T22:33:12.974155"
  },
  "fundamentals_BAF_VN": {
    "updated": "2026-05-26T22:33:21.588226"
  },
  "fundamentals_5274O_TW": {
    "updated": "2026-05-26T23:09:24.195282"
  },
  "fundamentals_5347O_TW": {
    "updated": "2026-05-26T23:09:34.981514"
  },
  "fundamentals_8299O_TW": {
    "updated": "2026-05-26T23:09:42.053584"
  },
  "fundamentals_8096O_TW": {
    "updated": "2026-05-26T23:09:44.055204"
  },
  "fundamentals_6488O_TW": {
    "updated": "2026-05-26T23:09:51.182779"
  },
  "fundamentals_4908O_TW": {
    "updated": "2026-05-26T23:10:38.550763"
  },
  "fundamentals_8069O_TW": {
    "updated": "2026-05-26T23:11:10.016748"
  },
  "price_EIB_VN": {
    "updated": "2026-06-01T21:18:42.422182",
    "rows": 268,
    "start": "2025-05-06 00:00:00",
    "end": "2026-06-01 00:00:00"
  },
  "price_OCB_VN": {
    "updated": "2026-06-01T21:18:51.814813",
    "rows": 159,
    "start": "2025-10-08 00:00:00",
    "end": "2026-06-01 00:00:00"
  },
  "price_DXG_VN": {
    "updated": "2026-06-01T21:20:29.131421",
    "rows": 268,
    "start": "2025-05-06 00:00:00",
    "end": "2026-06-01 00:00:00"
  },
  "price_TDC_VN": {
    "updated": "2026-06-01T21:20:45.529058",
    "rows": 268,
    "start": "2025-05-06 00:00:00",
    "end": "2026-06-01 00:00:00"
  },
  "price_VPI_VN": {
    "updated": "2026-06-01T21:21:26.890946",
    "rows": 268,
    "start": "2025-05-06 00:00:00",
    "end": "2026-06-01 00:00:00"
  },
  "price_PC1_VN": {
    "updated": "2026-06-01T21:22:35.229738",
    "rows": 268,
    "start": "2025-05-06 00:00:00",
    "end": "2026-06-01 00:00:00"
  },
  "price_SZC_VN": {
    "updated": "2026-06-01T21:23:14.267754",
    "rows": 254,
    "start": "2025-05-26 00:00:00",
    "end": "2026-06-01 00:00:00"
  },
  "price_DPR_VN": {
    "updated": "2026-06-01T21:25:22.746836",
    "rows": 277,
    "start": "2025-05-06 00:00:00",
    "end": "2026-05-29 00:00:00"
  },
  "price_TRC_VN": {
    "updated": "2026-06-01T21:25:34.855485",
    "rows": 268,
    "start": "2025-05-06 00:00:00",
    "end": "2026-06-01 00:00:00"
  },
  "price_LSS_VN": {
    "updated": "2026-06-01T21:26:01.990055",
    "rows": 268,
    "start": "2025-05-06 00:00:00",
    "end": "2026-06-01 00:00:00"
  },
  "price_GEG_VN": {
    "updated": "2026-06-01T21:26:40.544967",
    "rows": 268,
    "start": "2025-05-06 00:00:00",
    "end": "2026-06-01 00:00:00"
  },
  "price_TLH_VN": {
    "updated": "2026-06-01T21:27:27.747663",
    "rows": 159,
    "start": "2025-10-08 00:00:00",
    "end": "2026-06-01 00:00:00"
  },
  "price_SMC_VN": {
    "updated": "2026-06-01T21:27:32.783472",
    "rows": 254,
    "start": "2025-05-26 00:00:00",
    "end": "2026-06-01 00:00:00"
  },
  "price_HSG_VN": {
    "updated": "2026-06-01T21:27:38.308663",
    "rows": 254,
    "start": "2025-05-26 00:00:00",
    "end": "2026-06-01 00:00:00"
  },
  "price_DHC_VN": {
    "updated": "2026-06-01T21:28:47.472286",
    "rows": 21,
    "start": "2026-05-04 00:00:00",
    "end": "2026-06-01 00:00:00"
  },
  "price_HAX_VN": {
    "updated": "2026-06-01T21:29:23.755714",
    "rows": 268,
    "start": "2025-05-06 00:00:00",
    "end": "2026-06-01 00:00:00"
  },
  "price_HAH_VN": {
    "updated": "2026-06-01T21:29:33.347132",
    "rows": 268,
    "start": "2025-05-06 00:00:00",
    "end": "2026-06-01 00:00:00"
  },
  "price_VNE_VN": {
    "updated": "2026-06-01T21:30:34.555455",
    "rows": 268,
    "start": "2025-05-06 00:00:00",
    "end": "2026-06-01 00:00:00"
  },
  "price_SGT_VN": {
    "updated": "2026-06-01T21:30:39.309463",
    "rows": 252,
    "start": "2025-05-26 00:00:00",
    "end": "2026-06-01 00:00:00"
  },
  "price_HVN_VN": {
    "updated": "2026-06-01T21:31:01.181894",
    "rows": 254,
    "start": "2025-05-26 00:00:00",
    "end": "2026-06-01 00:00:00"
  },
  "price_HCM_VN": {
    "updated": "2026-06-01T21:31:28.677800",
    "rows": 268,
    "start": "2025-05-06 00:00:00",
    "end": "2026-06-01 00:00:00"
  },
  "price_ORS_VN": {
    "updated": "2026-06-01T21:31:55.290216",
    "rows": 268,
    "start": "2025-05-06 00:00:00",
    "end": "2026-06-01 00:00:00"
  },
  "price_FTS_VN": {
    "updated": "2026-06-01T21:32:14.697768",
    "rows": 268,
    "start": "2025-05-06 00:00:00",
    "end": "2026-06-01 00:00:00"
  },
  "price_FCN_VN": {
    "updated": "2026-06-01T21:32:43.515843",
    "rows": 268,
    "start": "2025-05-06 00:00:00",
    "end": "2026-06-01 00:00:00"
  },
  "price_DHG_VN": {
    "updated": "2026-06-01T21:33:27.099755",
    "rows": 263,
    "start": "2025-05-26 00:00:00",
    "end": "2026-05-29 00:00:00"
  },
  "price_IMP_VN": {
    "updated": "2026-06-01T21:33:32.118173",
    "rows": 254,
    "start": "2025-05-26 00:00:00",
    "end": "2026-06-01 00:00:00"
  },
  "price_TRA_VN": {
    "updated": "2026-06-01T21:33:36.782030",
    "rows": 159,
    "start": "2025-10-08 00:00:00",
    "end": "2026-06-01 00:00:00"
  },
  "fundamentals_2484_TW_TW": {
    "updated": "2026-06-01T22:55:51.371605"
  },
  "fundamentals_6770_TW_TW": {
    "updated": "2026-06-01T22:56:31.515413"
  },
  "fundamentals_2404_TW_TW": {
    "updated": "2026-06-01T23:05:14.072005"
  },
  "fundamentals_3481_TW_TW": {
    "updated": "2026-06-01T23:05:14.348060"
  },
  "fundamentals_2352_TW_TW": {
    "updated": "2026-06-01T23:05:14.638402"
  },
  "fundamentals_2451_TW_TW": {
    "updated": "2026-06-01T23:05:14.925510"
  },
  "fundamentals_5388_TW_TW": {
    "updated": "2026-06-01T23:05:15.213857"
  },
  "fundamentals_2360_TW_TW": {
    "updated": "2026-06-01T23:05:15.595047"
  },
  "fundamentals_6770_TW": {
    "updated": "2026-06-01T23:07:05.228231"
  },
  "fundamentals_2484_TW": {
    "updated": "2026-06-01T23:07:05.497176"
  },
  "fundamentals_2404_TW": {
    "updated": "2026-06-01T23:07:05.775315"
  },
  "fundamentals_2352_TW": {
    "updated": "2026-06-01T23:07:06.052869"
  },
  "fundamentals_2451_TW": {
    "updated": "2026-06-01T23:07:06.433697"
  },
  "fundamentals_5388_TW": {
    "updated": "2026-06-01T23:07:06.709349"
  },
  "fundamentals_2360_TW": {
    "updated": "2026-06-01T23:07:06.979111"
  }
}